hypercoil/__about__.py
hypercoil/__init__.py
hypercoil/downstream/test_globe.py
hypercoil/downstream/test_qcfc.py
hypercoil/downstream/data/__init__.py
hypercoil/downstream/data/bids.py
hypercoil/downstream/data/collate.py
hypercoil/downstream/data/dataref.py
hypercoil/downstream/data/dataset.py
hypercoil/downstream/data/functional.py
hypercoil/downstream/data/grabber.py
hypercoil/downstream/data/hcp.py
hypercoil/downstream/data/neuro.py
hypercoil/downstream/data/transforms.py
hypercoil/downstream/data/variables.py
hypercoil/downstream/data/wds.py
hypercoil/downstream/data/test/test_dataset.py
hypercoil/downstream/data/test/test_transforms.py
hypercoil/downstream/engine/accumulate.py
hypercoil/downstream/engine/action.py
hypercoil/downstream/engine/conveyance.py
hypercoil/downstream/engine/ephemeral.py
hypercoil/downstream/engine/report.py
hypercoil/downstream/engine/schedule.py
hypercoil/downstream/engine/sentry.py
hypercoil/downstream/engine/terminal.py
hypercoil/downstream/engine/test/test_accumulate.py
hypercoil/downstream/engine/test/test_ephemeral.py
hypercoil/downstream/engine/test/test_schedule.py
hypercoil/downstream/engine/test/test_terminal.py
hypercoil/downstream/eval/__init__.py
hypercoil/downstream/eval/atlas.py
hypercoil/downstream/eval/denoise.py
hypercoil/downstream/examples/synthetic/experiments/svm.py
hypercoil/downstream/examples/synthetic/scripts/svm.py
hypercoil/downstream/init/geomcompress.py
hypercoil/downstream/init/test/test_geomcompress.py
hypercoil/downstream/nn/svm.py
hypercoil/downstream/nn/test/test_netsvm.py
hypercoil/downstream/viz/filter.py
hypercoil/downstream/viz/globe.py
hypercoil/downstream/viz/parcelbm.py
hypercoil/downstream/viz/qcfc.py
hypercoil/downstream/viz/surfplot.py
hypercoil/downstream/viz/surfutils.py
hypercoil/downstream/workflows/atlasbenchmark.py
hypercoil/downstream/workflows/atlassub.py
hypercoil/downstream/workflows/denoisebenchmark.py
hypercoil/downstream/workflows/entropycascade.py
hypercoil-0.1.0.dev1.dist-info/LICENSE
hypercoil-0.1.0.dev1.dist-info/METADATA
hypercoil-0.1.0.dev1.dist-info/WHEEL
hypercoil-0.1.0.dev1.dist-info/top_level.txt
hypercoil-0.1.0.dev1.dist-info/RECORD
