Metadata-Version: 2.1
Name: hypercoil
Version: 0.1.0.dev1
Summary: Differentiable programming for neuroimaging analysis
Author-email: PROJECT developers <rastko@stanford.edu>
Maintainer-email: PROJECT developers <rastko@stanford.edu>
License: Apache License
Project-URL: Homepage, https://github.com/hypercoil/hypercoil
Classifier: Programming Language :: Python :: 3
Classifier: License :: OSI Approved :: Apache Software License
Classifier: Operating System :: POSIX :: Linux
Classifier: Operating System :: MacOS :: MacOS X
Classifier: Development Status :: 1 - Planning
Classifier: Environment :: Console
Classifier: Environment :: GPU :: NVIDIA CUDA
Classifier: Intended Audience :: Science/Research
Classifier: Topic :: Scientific/Engineering :: Artificial Intelligence
Classifier: Topic :: Scientific/Engineering :: Bio-Informatics
Classifier: Topic :: Scientific/Engineering :: Image Processing
Classifier: Topic :: Scientific/Engineering :: Medical Science Apps.
Requires-Python: >=3.10
License-File: LICENSE
Requires-Dist: jax >=0.3.16
Requires-Dist: equinox >=0.7.1
Requires-Dist: numpyro
Requires-Dist: optax >=0.1.3
Requires-Dist: numpy >=1.22.4
Requires-Dist: pandas >=1.4.3
Requires-Dist: nibabel >=4.0.1
Requires-Dist: scipy >=1.9.0
Requires-Dist: templateflow >=0.8.1
Requires-Dist: lytemaps
Requires-Dist: click
Requires-Dist: requests
Provides-Extra: doc
Requires-Dist: sphinx ; extra == 'doc'
Provides-Extra: test
Requires-Dist: matplotlib ; extra == 'test'
Requires-Dist: scikit-image ; extra == 'test'
Requires-Dist: pingouin ; extra == 'test'
Requires-Dist: nilearn ; extra == 'test'
Requires-Dist: communities ; extra == 'test'
Requires-Dist: brainspace ; extra == 'test'
Requires-Dist: hypercoil-examples ; extra == 'test'
Requires-Dist: hyve-examples ; extra == 'test'
Requires-Dist: pytest ; extra == 'test'
Requires-Dist: pytest-cov ; extra == 'test'
Requires-Dist: coverage[toml] ; extra == 'test'
Requires-Dist: ruff ; extra == 'test'
Requires-Dist: blue ; extra == 'test'
Provides-Extra: viz
Requires-Dist: hyve >=0.0.2.dev1 ; extra == 'viz'
